[
  {
    "name": "GLADIUS",
    "nightlord": "GLADIUS",
    "night": "NIGHTLORD",
    "standard": null,
    "slash": null,
    "strike": null,
    "pierce": -10,
    "magic": null,
    "fire": 50,
    "lightning": null,
    "holy": -35,
    "poison": 542,
    "rot": 252,
    "bleed": 252,
    "frostbite": 542,
    "sleep": 154,
    "madness": null
  },
  {
    "name": "DEMI-HUMAN QUEEN",
    "nightlord": "GLADIUS",
    "night": "NIGHT 1",
    "standard": null,
    "slash": -10,
    "strike": null,
    "pierce": null,
    "magic": -20,
    "fire": null,
    "lightning": null,
    "holy": null,
    "poison": 84,
    "rot": 84,
    "bleed": 112,
    "frostbite": 112,
    "sleep": 112,
    "madness": null
  },
  {
    "name": "DEMI-HUMAN SWORDMASTER",
    "nightlord": "GLADIUS",
    "night": "NIGHT 1",
    "standard": null,
    "slash": -20,
    "strike": null,
    "pierce": null,
    "magic": -20,
    "fire": null,
    "lightning": null,
    "holy": null,
    "poison": 84,
    "rot": 84,
    "bleed": 112,
    "frostbite": 112,
    "sleep": 112,
    "madness": null
  },
  {
    "name": "BELL BEARING HUNTER",
    "nightlord": "GLADIUS",
    "night": "NIGHT 1",
    "standard": 35,
    "slash": 35,
    "strike": 35,
    "pierce": 10,
    "magic": 40,
    "fire": 40,
    "lightning": 20,
    "holy": 40,
    "poison": 154,
    "rot": 154,
    "bleed": 252,
    "frostbite": 252,
    "sleep": 154,
    "madness": null
  },
  {
    "name": "FELL OMEN",
    "nightlord": "GLADIUS",
    "night": "NIGHT 2",
    "standard": null,
    "slash": -10,
    "strike": null,
    "pierce": null,
    "magic": null,
    "fire": null,
    "lightning": null,
    "holy": 40,
    "poison": 154,
    "rot": 154,
    "bleed": 154,
    "frostbite": 154,
    "sleep": 252,
    "madness": null
  },
  {
    "name": "TREE SENTINEL",
    "nightlord": "GLADIUS",
    "night": "NIGHT 2",
    "standard": 10,
    "slash": 35,
    "strike": 10,
    "pierce": 10,
    "magic": 20,
    "fire": 40,
    "lightning": null,
    "holy": 40,
    "poison": 154,
    "rot": 154,
    "bleed": 252,
    "frostbite": 252,
    "sleep": 154,
    "madness": null
  },
  {
    "name": "ROYAL CAVALRY",
    "nightlord": "GLADIUS",
    "night": "NIGHT 2",
    "standard": 10,
    "slash": 35,
    "strike": 10,
    "pierce": null,
    "magic": 20,
    "fire": 20,
    "lightning": 40,
    "holy": 20,
    "poison": 112,
    "rot": 112,
    "bleed": 154,
    "frostbite": 154,
    "sleep": 112,
    "madness": null
  },
  {
    "name": "ADEL",
    "nightlord": "ADEL",
    "night": "NIGHTLORD",
    "standard": null,
    "slash": null,
    "strike": null,
    "pierce": null,
    "magic": null,
    "fire": 20,
    "lightning": 40,
    "holy": null,
    "poison": 154,
    "rot": 154,
    "bleed": 542,
    "frostbite": 154,
    "sleep": 154,
    "madness": null
  },
  {
    "name": "DUKE'S DEAR FREJA",
    "nightlord": "ADEL",
    "night": "NIGHT 1",
    "standard": 16,
    "slash": 7,
    "strike": -10,
    "pierce": 30,
    "magic": 50,
    "fire": 30,
    "lightning": 50,
    "holy": 50,
    "poison": null,
    "rot": 252,
    "bleed": 252,
    "frostbite": 252,
    "sleep": null,
    "madness": null
  },
  {
    "name": "GAPING DRAGON",
    "nightlord": "ADEL",
    "night": "NIGHT 1",
    "standard": null,
    "slash": null,
    "strike": null,
    "pierce": null,
    "magic": -10,
    "fire": -15,
    "lightning": -20,
    "holy": -10,
    "poison": null,
    "rot": null,
    "bleed": 154,
    "frostbite": 154,
    "sleep": null,
    "madness": null
  },
  {
    "name": "NIGHT'S CAVALRY",
    "nightlord": "ADEL",
    "night": "NIGHT 1",
    "standard": 35,
    "slash": 35,
    "strike": 35,
    "pierce": 10,
    "magic": 40,
    "fire": 40,
    "lightning": 20,
    "holy": 40,
    "poison": 154,
    "rot": 154,
    "bleed": 252,
    "frostbite": 252,
    "sleep": null,
    "madness": null
  },
  {
    "name": "VALIENT GARGOYLE",
    "nightlord": "ADEL",
    "night": "NIGHT 1",
    "standard": 10,
    "slash": 35,
    "strike": null,
    "pierce": 35,
    "magic": 20,
    "fire": 40,
    "lightning": 40,
    "holy": 40,
    "poison": null,
    "rot": null,
    "bleed": null,
    "frostbite": null,
    "sleep": null,
    "madness": null
  },
  {
    "name": "WORMFACE",
    "nightlord": "ADEL",
    "night": "NIGHT 1",
    "standard": null,
    "slash": -10,
    "strike": null,
    "pierce": null,
    "magic": null,
    "fire": null,
    "lightning": null,
    "holy": 40,
    "poison": 308,
    "rot": 231,
    "bleed": 231,
    "frostbite": 231,
    "sleep": 231,
    "madness": null
  },
  {
    "name": "ANCIENT DRAGON",
    "nightlord": "ADEL",
    "night": "NIGHT 2",
    "standard": 35,
    "slash": 35,
    "strike": 35,
    "pierce": 10,
    "magic": 40,
    "fire": 40,
    "lightning": 80,
    "holy": 40,
    "poison": 252,
    "rot": 252,
    "bleed": 252,
    "frostbite": 252,
    "sleep": null,
    "madness": null
  },
  {
    "name": "OUTLAND COMMANDER",
    "nightlord": "ADEL",
    "night": "NIGHT 2",
    "standard": 10,
    "slash": 35,
    "strike": 10,
    "pierce": null,
    "magic": 20,
    "fire": 20,
    "lightning": 20,
    "holy": 20,
    "poison": 154,
    "rot": 154,
    "bleed": 154,
    "frostbite": 154,
    "sleep": 154,
    "madness": null
  },
  {
    "name": "GOLDEN HIPPOPOTAMUS",
    "nightlord": "ADEL",
    "night": "NIGHT 2",
    "standard": null,
    "slash": -10,
    "strike": null,
    "pierce": null,
    "magic": null,
    "fire": null,
    "lightning": -20,
    "holy": -20,
    "poison": 154,
    "rot": 154,
    "bleed": 252,
    "frostbite": 252,
    "sleep": null,
    "madness": null
  },
  {
    "name": "CRUCIBLE KNIGHT",
    "nightlord": "ADEL",
    "night": "NIGHT 2",
    "standard": 35,
    "slash": 35,
    "strike": 35,
    "pierce": 35,
    "magic": 40,
    "fire": 20,
    "lightning": 20,
    "holy": 40,
    "poison": 252,
    "rot": 252,
    "bleed": null,
    "frostbite": 252,
    "sleep": 252,
    "madness": null
  },
  {
    "name": "GNOSTER (MOTH)",
    "nightlord": "GNOSTER",
    "night": "NIGHTLORD",
    "standard": -15,
    "slash": -25,
    "strike": -15,
    "pierce": -25,
    "magic": 50,
    "fire": -40,
    "lightning": 10,
    "holy": 10,
    "poison": 542,
    "rot": 154,
    "bleed": 154,
    "frostbite": 154,
    "sleep": 542,
    "madness": null
  },
  {
    "name": "FAURTIS (SCORPION)",
    "nightlord": "GNOSTER",
    "night": "NIGHTLORD",
    "standard": 10,
    "slash": 20,
    "strike": -20,
    "pierce": -10,
    "magic": 10,
    "fire": -35,
    "lightning": 10,
    "holy": 10,
    "poison": 252,
    "rot": 154,
    "bleed": 154,
    "frostbite": 154,
    "sleep": 154,
    "madness": null
  },
  {
    "name": "ANIMUS",
    "nightlord": "GNOSTER",
    "night": "NIGHTLORD",
    "standard": null,
    "slash": null,
    "strike": null,
    "pierce": null,
    "magic": null,
    "fire": null,
    "lightning": null,
    "holy": null,
    "poison": null,
    "rot": null,
    "bleed": null,
    "frostbite": null,
    "sleep": null,
    "madness": null
  },
  {
    "name": "BATTLEFIELD COMMANDER",
    "nightlord": "GNOSTER",
    "night": "NIGHT 1",
    "standard": 10,
    "slash": 35,
    "strike": 10,
    "pierce": null,
    "magic": 20,
    "fire": 20,
    "lightning": 20,
    "holy": 20,
    "poison": 154,
    "rot": 154,
    "bleed": 154,
    "frostbite": 154,
    "sleep": 154,
    "madness": null
  },
  {
    "name": "CENTIPED DEMON",
    "nightlord": "GNOSTER",
    "night": "NIGHT 1",
    "standard": null,
    "slash": null,
    "strike": -10,
    "pierce": null,
    "magic": -20,
    "fire": 80,
    "lightning": -10,
    "holy": -10,
    "poison": 252,
    "rot": 252,
    "bleed": 252,
    "frostbite": 252,
    "sleep": null,
    "madness": null
  },
  {
    "name": "SMELTER DEMON",
    "nightlord": "GNOSTER",
    "night": "NIGHT 1",
    "standard": -10,
    "slash": 6,
    "strike": -10,
    "pierce": 8,
    "magic": 30,
    "fire": 80,
    "lightning": 30,
    "holy": 30,
    "poison": 154,
    "rot": 154,
    "bleed": null,
    "frostbite": 252,
    "sleep": null,
    "madness": null
  },
  {
    "name": "TIBIA MARINER",
    "nightlord": "GNOSTER",
    "night": "NIGHT 1",
    "standard": 10,
    "slash": 10,
    "strike": -40,
    "pierce": 35,
    "magic": 20,
    "fire": 20,
    "lightning": 40,
    "holy": -40,
    "poison": null,
    "rot": 154,
    "bleed": null,
    "frostbite": null,
    "sleep": null,
    "madness": null
  },
  {
    "name": "DRACO. TREE SENTINEL",
    "nightlord": "GNOSTER",
    "night": "NIGHT 2",
    "standard": 10,
    "slash": 35,
    "strike": 10,
    "pierce": 10,
    "magic": 20,
    "fire": 40,
    "lightning": 40,
    "holy": 40,
    "poison": 154,
    "rot": 154,
    "bleed": 252,
    "frostbite": 252,
    "sleep": 154,
    "madness": null
  },
  {
    "name": "ROYAL CAVALRY",
    "nightlord": "GNOSTER",
    "night": "NIGHT 2",
    "standard": 10,
    "slash": 35,
    "strike": 10,
    "pierce": null,
    "magic": 20,
    "fire": 20,
    "lightning": 40,
    "holy": 20,
    "poison": 112,
    "rot": 112,
    "bleed": 154,
    "frostbite": 154,
    "sleep": 112,
    "madness": null
  },
  {
    "name": "GREAT WYRM",
    "nightlord": "GNOSTER",
    "night": "NIGHT 2",
    "standard": 10,
    "slash": 35,
    "strike": 10,
    "pierce": 10,
    "magic": 40,
    "fire": 80,
    "lightning": 40,
    "holy": 40,
    "poison": 252,
    "rot": 252,
    "bleed": 252,
    "frostbite": 542,
    "sleep": 112,
    "madness": null
  },
  {
    "name": "NOX DRAGONKIN",
    "nightlord": "GNOSTER",
    "night": "NIGHT 2",
    "standard": 10,
    "slash": null,
    "strike": 10,
    "pierce": 10,
    "magic": 20,
    "fire": 20,
    "lightning": 40,
    "holy": 20,
    "poison": 252,
    "rot": 252,
    "bleed": 252,
    "frostbite": 542,
    "sleep": null,
    "madness": null
  },
  {
    "name": "MARIS",
    "nightlord": "MARIS",
    "night": "NIGHTLORD",
    "standard": null,
    "slash": -15,
    "strike": 20,
    "pierce": 10,
    "magic": 20,
    "fire": 50,
    "lightning": -40,
    "holy": 15,
    "poison": null,
    "rot": 252,
    "bleed": null,
    "frostbite": 252,
    "sleep": null,
    "madness": null
  },
  {
    "name": "GAPING DRAGON",
    "nightlord": "MARIS",
    "night": "NIGHT 1",
    "standard": null,
    "slash": null,
    "strike": null,
    "pierce": null,
    "magic": -10,
    "fire": -15,
    "lightning": -20,
    "holy": -10,
    "poison": null,
    "rot": null,
    "bleed": 154,
    "frostbite": 154,
    "sleep": null,
    "madness": null
  },
  {
    "name": "GRAFTED MONARCH",
    "nightlord": "MARIS",
    "night": "NIGHT 1",
    "standard": null,
    "slash": null,
    "strike": null,
    "pierce": null,
    "magic": 20,
    "fire": 20,
    "lightning": 20,
    "holy": 40,
    "poison": 154,
    "rot": 154,
    "bleed": 154,
    "frostbite": 154,
    "sleep": 154,
    "madness": null
  },
  {
    "name": "SMELTER DEMON",
    "nightlord": "MARIS",
    "night": "NIGHT 1",
    "standard": -10,
    "slash": 6,
    "strike": -10,
    "pierce": 8,
    "magic": 30,
    "fire": 80,
    "lightning": 30,
    "holy": 30,
    "poison": 154,
    "rot": 154,
    "bleed": null,
    "frostbite": 252,
    "sleep": null,
    "madness": null
  },
  {
    "name": "VALIENT GARGOYLE",
    "nightlord": "MARIS",
    "night": "NIGHT 1",
    "standard": 10,
    "slash": 35,
    "strike": null,
    "pierce": 35,
    "magic": 20,
    "fire": 40,
    "lightning": 40,
    "holy": 40,
    "poison": null,
    "rot": null,
    "bleed": null,
    "frostbite": null,
    "sleep": null,
    "madness": null
  },
  {
    "name": "WORMFACE",
    "nightlord": "MARIS",
    "night": "NIGHT 1",
    "standard": null,
    "slash": -10,
    "strike": null,
    "pierce": null,
    "magic": null,
    "fire": null,
    "lightning": null,
    "holy": 40,
    "poison": 308,
    "rot": 231,
    "bleed": 231,
    "frostbite": 231,
    "sleep": 231,
    "madness": null
  },
  {
    "name": "GODSKIN NOBLE",
    "nightlord": "MARIS",
    "night": "NIGHT 2",
    "standard": null,
    "slash": -10,
    "strike": 35,
    "pierce": null,
    "magic": 20,
    "fire": 40,
    "lightning": 20,
    "holy": 40,
    "poison": 154,
    "rot": 154,
    "bleed": 112,
    "frostbite": 154,
    "sleep": 112,
    "madness": null
  },
  {
    "name": "GODSKIN APOSTLE",
    "nightlord": "MARIS",
    "night": "NIGHT 2",
    "standard": null,
    "slash": -10,
    "strike": 10,
    "pierce": null,
    "magic": 20,
    "fire": 40,
    "lightning": 20,
    "holy": 40,
    "poison": 154,
    "rot": 154,
    "bleed": 112,
    "frostbite": 154,
    "sleep": 112,
    "madness": null
  },
  {
    "name": "FALLINGSTAR BEAST",
    "nightlord": "MARIS",
    "night": "NIGHT 2",
    "standard": 35,
    "slash": 35,
    "strike": 35,
    "pierce": 35,
    "magic": 20,
    "fire": 20,
    "lightning": 20,
    "holy": 20,
    "poison": null,
    "rot": null,
    "bleed": null,
    "frostbite": null,
    "sleep": null,
    "madness": null
  },
  {
    "name": "TREE SENTINEL",
    "nightlord": "MARIS",
    "night": "NIGHT 2",
    "standard": 10,
    "slash": 35,
    "strike": 10,
    "pierce": 10,
    "magic": 20,
    "fire": 40,
    "lightning": null,
    "holy": 40,
    "poison": 154,
    "rot": 154,
    "bleed": 252,
    "frostbite": 252,
    "sleep": 154,
    "madness": null
  },
  {
    "name": "ROYAL CAVALRY",
    "nightlord": "MARIS",
    "night": "NIGHT 2",
    "standard": 10,
    "slash": 35,
    "strike": 10,
    "pierce": null,
    "magic": 20,
    "fire": 20,
    "lightning": 40,
    "holy": 20,
    "poison": 112,
    "rot": 112,
    "bleed": 154,
    "frostbite": 154,
    "sleep": 112,
    "madness": null
  },
  {
    "name": "LIBRA",
    "nightlord": "LIBRA",
    "night": "NIGHTLORD",
    "standard": null,
    "slash": -10,
    "strike": null,
    "pierce": null,
    "magic": 20,
    "fire": -20,
    "lightning": null,
    "holy": -35,
    "poison": 154,
    "rot": 154,
    "bleed": 252,
    "frostbite": 252,
    "sleep": null,
    "madness": 154
  },
  {
    "name": "BATTLEFIELD COMMANDER",
    "nightlord": "LIBRA",
    "night": "NIGHT 1",
    "standard": 10,
    "slash": 35,
    "strike": 10,
    "pierce": null,
    "magic": 20,
    "fire": 20,
    "lightning": 20,
    "holy": 20,
    "poison": 154,
    "rot": 154,
    "bleed": 154,
    "frostbite": 154,
    "sleep": 154,
    "madness": null
  },
  {
    "name": "CENTIPEDE DEMON",
    "nightlord": "LIBRA",
    "night": "NIGHT 1",
    "standard": null,
    "slash": null,
    "strike": -10,
    "pierce": null,
    "magic": -20,
    "fire": 80,
    "lightning": -10,
    "holy": -10,
    "poison": 252,
    "rot": 252,
    "bleed": 252,
    "frostbite": 252,
    "sleep": null,
    "madness": null
  },
  {
    "name": "DUKE'S DEAR FREJA",
    "nightlord": "LIBRA",
    "night": "NIGHT 1",
    "standard": 16,
    "slash": 7,
    "strike": -10,
    "pierce": 30,
    "magic": 50,
    "fire": 30,
    "lightning": 50,
    "holy": 50,
    "poison": null,
    "rot": 252,
    "bleed": 252,
    "frostbite": 252,
    "sleep": null,
    "madness": null
  },
  {
    "name": "ROYAL REVENANT",
    "nightlord": "LIBRA",
    "night": "NIGHT 1",
    "standard": null,
    "slash": -10,
    "strike": null,
    "pierce": null,
    "magic": null,
    "fire": null,
    "lightning": null,
    "holy": 40,
    "poison": 154,
    "rot": 154,
    "bleed": 154,
    "frostbite": 154,
    "sleep": null,
    "madness": null
  },
  {
    "name": "TIBIA MARINER",
    "nightlord": "LIBRA",
    "night": "NIGHT 1",
    "standard": 10,
    "slash": 10,
    "strike": -40,
    "pierce": 35,
    "magic": 20,
    "fire": 20,
    "lightning": 40,
    "holy": -40,
    "poison": null,
    "rot": 154,
    "bleed": null,
    "frostbite": null,
    "sleep": null,
    "madness": null
  },
  {
    "name": "CRUCIBLE KNIGHT",
    "nightlord": "LIBRA",
    "night": "NIGHT 2",
    "standard": 35,
    "slash": 35,
    "strike": 35,
    "pierce": 35,
    "magic": 40,
    "fire": 20,
    "lightning": 20,
    "holy": 40,
    "poison": 252,
    "rot": 252,
    "bleed": null,
    "frostbite": 252,
    "sleep": 252,
    "madness": null
  },
  {
    "name": "GOLDEN HIPPO",
    "nightlord": "LIBRA",
    "night": "NIGHT 2",
    "standard": null,
    "slash": -10,
    "strike": null,
    "pierce": null,
    "magic": -20,
    "fire": -20,
    "lightning": null,
    "holy": null,
    "poison": 154,
    "rot": 154,
    "bleed": 252,
    "frostbite": 252,
    "sleep": null,
    "madness": null
  },
  {
    "name": "DEATH RITE BIRD",
    "nightlord": "LIBRA",
    "night": "NIGHT 2",
    "standard": 10,
    "slash": 10,
    "strike": -40,
    "pierce": 35,
    "magic": 20,
    "fire": 20,
    "lightning": 40,
    "holy": -40,
    "poison": null,
    "rot": 252,
    "bleed": null,
    "frostbite": null,
    "sleep": null,
    "madness": null
  },
  {
    "name": "GODSKIN NOBLE",
    "nightlord": "LIBRA",
    "night": "NIGHT 2",
    "standard": null,
    "slash": -10,
    "strike": null,
    "pierce": 35,
    "magic": 20,
    "fire": 40,
    "lightning": 20,
    "holy": 40,
    "poison": 154,
    "rot": 154,
    "bleed": 112,
    "frostbite": 154,
    "sleep": 112,
    "madness": null
  },
  {
    "name": "GODSKIN APOSTLE",
    "nightlord": "LIBRA",
    "night": "NIGHT 2",
    "standard": null,
    "slash": -10,
    "strike": null,
    "pierce": 10,
    "magic": 20,
    "fire": 40,
    "lightning": 20,
    "holy": 40,
    "poison": 154,
    "rot": 154,
    "bleed": 112,
    "frostbite": 154,
    "sleep": 112,
    "madness": null
  },
  {
    "name": "FULGHOR",
    "nightlord": "FULGHOR",
    "night": "NIGHTLORD",
    "standard": null,
    "slash": null,
    "strike": null,
    "pierce": null,
    "magic": null,
    "fire": null,
    "lightning": -20,
    "holy": 40,
    "poison": 154,
    "rot": 154,
    "bleed": 154,
    "frostbite": 154,
    "sleep": 154,
    "madness": null
  },
  {
    "name": "CENTIPED DEMON",
    "nightlord": "FULGHOR",
    "night": "NIGHT 1",
    "standard": null,
    "slash": -10,
    "strike": null,
    "pierce": null,
    "magic": -20,
    "fire": 80,
    "lightning": -10,
    "holy": -10,
    "poison": 252,
    "rot": 252,
    "bleed": 252,
    "frostbite": 252,
    "sleep": null,
    "madness": null
  },
  {
    "name": "GAPING DRAGON",
    "nightlord": "FULGHOR",
    "night": "NIGHT 1",
    "standard": null,
    "slash": null,
    "strike": null,
    "pierce": null,
    "magic": -10,
    "fire": -15,
    "lightning": -20,
    "holy": -10,
    "poison": null,
    "rot": null,
    "bleed": 154,
    "frostbite": 154,
    "sleep": null,
    "madness": null
  },
  {
    "name": "NIGHT'S CAVALRY",
    "nightlord": "FULGHOR",
    "night": "NIGHT 1",
    "standard": 35,
    "slash": 35,
    "strike": 35,
    "pierce": 10,
    "magic": 40,
    "fire": 40,
    "lightning": 20,
    "holy": 40,
    "poison": 154,
    "rot": 154,
    "bleed": 252,
    "frostbite": 252,
    "sleep": null,
    "madness": null
  },
  {
    "name": "ROYAL REVENANT",
    "nightlord": "FULGHOR",
    "night": "NIGHT 1",
    "standard": null,
    "slash": -10,
    "strike": null,
    "pierce": null,
    "magic": null,
    "fire": null,
    "lightning": null,
    "holy": 40,
    "poison": 154,
    "rot": 154,
    "bleed": 154,
    "frostbite": 154,
    "sleep": null,
    "madness": null
  },
  {
    "name": "WORMFACE",
    "nightlord": "FULGHOR",
    "night": "NIGHT 1",
    "standard": null,
    "slash": -10,
    "strike": null,
    "pierce": null,
    "magic": null,
    "fire": null,
    "lightning": null,
    "holy": 40,
    "poison": 308,
    "rot": 231,
    "bleed": 231,
    "frostbite": 231,
    "sleep": 231,
    "madness": null
  },
  {
    "name": "KING OF THE STORM",
    "nightlord": "FULGHOR",
    "night": "NIGHT 2",
    "standard": 20,
    "slash": 21,
    "strike": 18,
    "pierce": 2,
    "magic": 10,
    "fire": 35,
    "lightning": -31,
    "holy": null,
    "poison": 252,
    "rot": 252,
    "bleed": 252,
    "frostbite": 154,
    "sleep": null,
    "madness": null
  },
  {
    "name": "NAMELESS KING",
    "nightlord": "FULGHOR",
    "night": "NIGHT 2",
    "standard": 21,
    "slash": 22,
    "strike": 19,
    "pierce": 20,
    "magic": 24,
    "fire": 23,
    "lightning": 83,
    "holy": -8,
    "poison": null,
    "rot": 252,
    "bleed": 252,
    "frostbite": 252,
    "sleep": null,
    "madness": null
  },
  {
    "name": "NOX DRAGONKIN",
    "nightlord": "FULGHOR",
    "night": "NIGHT 2",
    "standard": 10,
    "slash": null,
    "strike": 10,
    "pierce": 10,
    "magic": 20,
    "fire": 20,
    "lightning": 40,
    "holy": 20,
    "poison": 252,
    "rot": 252,
    "bleed": 252,
    "frostbite": 542,
    "sleep": null,
    "madness": null
  },
  {
    "name": "OUTLAND COMMANDER",
    "nightlord": "FULGHOR",
    "night": "NIGHT 2",
    "standard": 10,
    "slash": 35,
    "strike": 10,
    "pierce": null,
    "magic": 20,
    "fire": 20,
    "lightning": 20,
    "holy": 20,
    "poison": 154,
    "rot": 154,
    "bleed": 154,
    "frostbite": 154,
    "sleep": 154,
    "madness": null
  },
  {
    "name": "CALIGO",
    "nightlord": "CALIGO",
    "night": "NIGHTLORD",
    "standard": null,
    "slash": 15,
    "strike": -15,
    "pierce": 10,
    "magic": 20,
    "fire": -35,
    "lightning": 20,
    "holy": 20,
    "poison": 252,
    "rot": 252,
    "bleed": 252,
    "frostbite": 542,
    "sleep": 542,
    "madness": null
  },
  {
    "name": "DUKE'S DEAR FREJA",
    "nightlord": "CALIGO",
    "night": "NIGHT 1",
    "standard": 16,
    "slash": 7,
    "strike": -10,
    "pierce": 30,
    "magic": 50,
    "fire": 30,
    "lightning": 50,
    "holy": 50,
    "poison": null,
    "rot": 252,
    "bleed": 252,
    "frostbite": 252,
    "sleep": null,
    "madness": null
  },
  {
    "name": "GRAFTED MONARCH",
    "nightlord": "CALIGO",
    "night": "NIGHT 1",
    "standard": null,
    "slash": null,
    "strike": null,
    "pierce": null,
    "magic": 20,
    "fire": 20,
    "lightning": 20,
    "holy": 40,
    "poison": 154,
    "rot": 154,
    "bleed": 154,
    "frostbite": 154,
    "sleep": 154,
    "madness": null
  },
  {
    "name": "SMELTER DEMON",
    "nightlord": "CALIGO",
    "night": "NIGHT 1",
    "standard": -10,
    "slash": 6,
    "strike": -10,
    "pierce": 8,
    "magic": 30,
    "fire": 80,
    "lightning": 30,
    "holy": 30,
    "poison": 154,
    "rot": 154,
    "bleed": null,
    "frostbite": 252,
    "sleep": null,
    "madness": null
  },
  {
    "name": "TIBIA MARINER",
    "nightlord": "CALIGO",
    "night": "NIGHT 1",
    "standard": 10,
    "slash": 10,
    "strike": -40,
    "pierce": 35,
    "magic": 20,
    "fire": 20,
    "lightning": 40,
    "holy": -40,
    "poison": null,
    "rot": 154,
    "bleed": null,
    "frostbite": null,
    "sleep": null,
    "madness": null
  },
  {
    "name": "ULCERATED TREE SPIRIT",
    "nightlord": "CALIGO",
    "night": "NIGHT 1",
    "standard": null,
    "slash": null,
    "strike": null,
    "pierce": null,
    "magic": 20,
    "fire": -20,
    "lightning": 20,
    "holy": 40,
    "poison": 252,
    "rot": 252,
    "bleed": 252,
    "frostbite": 112,
    "sleep": null,
    "madness": null
  },
  {
    "name": "DANCER",
    "nightlord": "CALIGO",
    "night": "NIGHT 2",
    "standard": 20,
    "slash": 22,
    "strike": 19,
    "pierce": 20,
    "magic": 19,
    "fire": 18,
    "lightning": 17,
    "holy": -26,
    "poison": null,
    "rot": 252,
    "bleed": 252,
    "frostbite": null,
    "sleep": null,
    "madness": null
  },
  {
    "name": "DRACO. TREE SENTINEL",
    "nightlord": "CALIGO",
    "night": "NIGHT 2",
    "standard": 10,
    "slash": 35,
    "strike": 10,
    "pierce": 10,
    "magic": 20,
    "fire": 40,
    "lightning": 40,
    "holy": 40,
    "poison": 154,
    "rot": 154,
    "bleed": 252,
    "frostbite": 252,
    "sleep": 154,
    "madness": null
  },
  {
    "name": "ROYAL CAVALRY",
    "nightlord": "CALIGO",
    "night": "NIGHT 2",
    "standard": 10,
    "slash": 35,
    "strike": 10,
    "pierce": null,
    "magic": 20,
    "fire": 20,
    "lightning": 40,
    "holy": 20,
    "poison": 112,
    "rot": 112,
    "bleed": 154,
    "frostbite": 154,
    "sleep": 112,
    "madness": null
  },
  {
    "name": "GODSKIN NOBLE",
    "nightlord": "CALIGO",
    "night": "NIGHT 2",
    "standard": null,
    "slash": -10,
    "strike": 35,
    "pierce": null,
    "magic": 20,
    "fire": 40,
    "lightning": 20,
    "holy": 40,
    "poison": 154,
    "rot": 154,
    "bleed": 112,
    "frostbite": 154,
    "sleep": 112,
    "madness": null
  },
  {
    "name": "GODSKIN APOSTLE",
    "nightlord": "CALIGO",
    "night": "NIGHT 2",
    "standard": null,
    "slash": -10,
    "strike": 10,
    "pierce": null,
    "magic": 20,
    "fire": 40,
    "lightning": 20,
    "holy": 40,
    "poison": 154,
    "rot": 154,
    "bleed": 112,
    "frostbite": 154,
    "sleep": 112,
    "madness": null
  },
  {
    "name": "HEOLSTER (PHASE 1)",
    "nightlord": "HEOLSTER",
    "night": "NIGHTLORD",
    "standard": null,
    "slash": -15,
    "strike": 10,
    "pierce": null,
    "magic": -20,
    "fire": null,
    "lightning": null,
    "holy": -35,
    "poison": null,
    "rot": 252,
    "bleed": null,
    "frostbite": null,
    "sleep": 542,
    "madness": null
  },
  {
    "name": "HEOLSTER (PHASE 2)",
    "nightlord": "HEOLSTER",
    "night": "NIGHTLORD",
    "standard": null,
    "slash": null,
    "strike": null,
    "pierce": null,
    "magic": null,
    "fire": null,
    "lightning": null,
    "holy": null,
    "poison": null,
    "rot": null,
    "bleed": null,
    "frostbite": null,
    "sleep": null,
    "madness": null
  },
  {
    "name": "BATTLEFIELD COMMANDER",
    "nightlord": "HEOLSTER",
    "night": "NIGHT 1",
    "standard": null,
    "slash": null,
    "strike": null,
    "pierce": null,
    "magic": null,
    "fire": null,
    "lightning": null,
    "holy": null,
    "poison": null,
    "rot": null,
    "bleed": null,
    "frostbite": null,
    "sleep": null,
    "madness": null
  },
  {
    "name": "BELL BEARING HUNTER",
    "nightlord": "HEOLSTER",
    "night": "NIGHT 1",
    "standard": null,
    "slash": null,
    "strike": null,
    "pierce": null,
    "magic": null,
    "fire": null,
    "lightning": null,
    "holy": null,
    "poison": null,
    "rot": null,
    "bleed": null,
    "frostbite": null,
    "sleep": null,
    "madness": null
  },
  {
    "name": "CENTIPED DEMON",
    "nightlord": "HEOLSTER",
    "night": "NIGHT 1",
    "standard": null,
    "slash": null,
    "strike": null,
    "pierce": null,
    "magic": null,
    "fire": 80,
    "lightning": null,
    "holy": null,
    "poison": 252,
    "rot": 252,
    "bleed": 252,
    "frostbite": 252,
    "sleep": 252,
    "madness": null
  },
  {
    "name": "DEMI-HUMAN QUEEN",
    "nightlord": "HEOLSTER",
    "night": "NIGHT 1",
    "standard": null,
    "slash": null,
    "strike": null,
    "pierce": null,
    "magic": null,
    "fire": null,
    "lightning": null,
    "holy": null,
    "poison": null,
    "rot": null,
    "bleed": null,
    "frostbite": null,
    "sleep": null,
    "madness": null
  },
  {
    "name": "DEMI-HUMAN SWORDMASTER",
    "nightlord": "HEOLSTER",
    "night": "NIGHT 1",
    "standard": null,
    "slash": null,
    "strike": null,
    "pierce": null,
    "magic": null,
    "fire": null,
    "lightning": null,
    "holy": null,
    "poison": null,
    "rot": null,
    "bleed": null,
    "frostbite": null,
    "sleep": null,
    "madness": null
  },
  {
    "name": "GAPING DRAGON",
    "nightlord": "HEOLSTER",
    "night": "NIGHT 1",
    "standard": null,
    "slash": null,
    "strike": null,
    "pierce": null,
    "magic": null,
    "fire": null,
    "lightning": null,
    "holy": null,
    "poison": null,
    "rot": null,
    "bleed": null,
    "frostbite": null,
    "sleep": null,
    "madness": null
  },
  {
    "name": "NIGHT'S CAVALRY",
    "nightlord": "HEOLSTER",
    "night": "NIGHT 1",
    "standard": null,
    "slash": null,
    "strike": null,
    "pierce": null,
    "magic": null,
    "fire": null,
    "lightning": null,
    "holy": null,
    "poison": null,
    "rot": null,
    "bleed": null,
    "frostbite": null,
    "sleep": null,
    "madness": null
  },
  {
    "name": "ROYAL REVENANT",
    "nightlord": "HEOLSTER",
    "night": "NIGHT 1",
    "standard": null,
    "slash": null,
    "strike": null,
    "pierce": null,
    "magic": null,
    "fire": null,
    "lightning": null,
    "holy": null,
    "poison": null,
    "rot": null,
    "bleed": null,
    "frostbite": null,
    "sleep": null,
    "madness": null
  },
  {
    "name": "SMELTER DEMON",
    "nightlord": "HEOLSTER",
    "night": "NIGHT 1",
    "standard": null,
    "slash": null,
    "strike": null,
    "pierce": null,
    "magic": null,
    "fire": null,
    "lightning": null,
    "holy": null,
    "poison": null,
    "rot": null,
    "bleed": null,
    "frostbite": null,
    "sleep": null,
    "madness": null
  },
  {
    "name": "NIGHT'S CAVALRY",
    "nightlord": "HEOLSTER",
    "night": "NIGHT 1",
    "standard": null,
    "slash": null,
    "strike": null,
    "pierce": null,
    "magic": null,
    "fire": null,
    "lightning": null,
    "holy": null,
    "poison": null,
    "rot": null,
    "bleed": null,
    "frostbite": null,
    "sleep": null,
    "madness": null
  },
  {
    "name": "VALIENT GARGOYLE",
    "nightlord": "HEOLSTER",
    "night": "NIGHT 1",
    "standard": null,
    "slash": null,
    "strike": null,
    "pierce": null,
    "magic": null,
    "fire": null,
    "lightning": null,
    "holy": null,
    "poison": null,
    "rot": null,
    "bleed": null,
    "frostbite": null,
    "sleep": null,
    "madness": null
  },
  {
    "name": "ANCIENT DRAGON",
    "nightlord": "HEOLSTER",
    "night": "NIGHT 2",
    "standard": null,
    "slash": null,
    "strike": null,
    "pierce": null,
    "magic": null,
    "fire": null,
    "lightning": 80,
    "holy": null,
    "poison": 252,
    "rot": 252,
    "bleed": 252,
    "frostbite": 252,
    "sleep": 252,
    "madness": null
  },
  {
    "name": "CRUCIBLE KNIGHT",
    "nightlord": "HEOLSTER",
    "night": "NIGHT 2",
    "standard": null,
    "slash": null,
    "strike": null,
    "pierce": null,
    "magic": null,
    "fire": null,
    "lightning": null,
    "holy": null,
    "poison": null,
    "rot": null,
    "bleed": null,
    "frostbite": null,
    "sleep": null,
    "madness": null
  },
  {
    "name": "GOLDEN HIPPO",
    "nightlord": "HEOLSTER",
    "night": "NIGHT 2",
    "standard": null,
    "slash": null,
    "strike": null,
    "pierce": null,
    "magic": null,
    "fire": null,
    "lightning": null,
    "holy": null,
    "poison": null,
    "rot": null,
    "bleed": null,
    "frostbite": null,
    "sleep": null,
    "madness": null
  },
  {
    "name": "DANCER",
    "nightlord": "HEOLSTER",
    "night": "NIGHT 2",
    "standard": null,
    "slash": null,
    "strike": null,
    "pierce": null,
    "magic": null,
    "fire": null,
    "lightning": null,
    "holy": null,
    "poison": null,
    "rot": null,
    "bleed": null,
    "frostbite": null,
    "sleep": null,
    "madness": null
  },
  {
    "name": "DEATH RITE BIRD",
    "nightlord": "HEOLSTER",
    "night": "NIGHT 2",
    "standard": null,
    "slash": null,
    "strike": -40,
    "pierce": null,
    "magic": null,
    "fire": null,
    "lightning": null,
    "holy": -40,
    "poison": null,
    "rot": null,
    "bleed": null,
    "frostbite": null,
    "sleep": null,
    "madness": null
  },
  {
    "name": "DRACO. TREE SENTINEL",
    "nightlord": "HEOLSTER",
    "night": "NIGHT 2",
    "standard": null,
    "slash": null,
    "strike": null,
    "pierce": null,
    "magic": null,
    "fire": null,
    "lightning": null,
    "holy": null,
    "poison": null,
    "rot": null,
    "bleed": null,
    "frostbite": null,
    "sleep": null,
    "madness": null
  },
  {
    "name": "ROYAL CAVALRY",
    "nightlord": "HEOLSTER",
    "night": "NIGHT 2",
    "standard": null,
    "slash": null,
    "strike": null,
    "pierce": null,
    "magic": null,
    "fire": null,
    "lightning": null,
    "holy": null,
    "poison": null,
    "rot": null,
    "bleed": null,
    "frostbite": null,
    "sleep": null,
    "madness": null
  },
  {
    "name": "FALLINGSTAR BEAST",
    "nightlord": "HEOLSTER",
    "night": "NIGHT 2",
    "standard": null,
    "slash": null,
    "strike": null,
    "pierce": null,
    "magic": null,
    "fire": null,
    "lightning": null,
    "holy": null,
    "poison": null,
    "rot": null,
    "bleed": null,
    "frostbite": null,
    "sleep": null,
    "madness": null
  },
  {
    "name": "FELL OMEN",
    "nightlord": "HEOLSTER",
    "night": "NIGHT 2",
    "standard": null,
    "slash": null,
    "strike": null,
    "pierce": null,
    "magic": null,
    "fire": null,
    "lightning": null,
    "holy": null,
    "poison": null,
    "rot": null,
    "bleed": null,
    "frostbite": null,
    "sleep": null,
    "madness": null
  },
  {
    "name": "GREAT WYRM",
    "nightlord": "HEOLSTER",
    "night": "NIGHT 2",
    "standard": null,
    "slash": null,
    "strike": null,
    "pierce": null,
    "magic": null,
    "fire": null,
    "lightning": null,
    "holy": null,
    "poison": null,
    "rot": null,
    "bleed": null,
    "frostbite": null,
    "sleep": null,
    "madness": null
  },
  {
    "name": "KING OF THE STORM",
    "nightlord": "HEOLSTER",
    "night": "NIGHT 2",
    "standard": null,
    "slash": null,
    "strike": null,
    "pierce": null,
    "magic": null,
    "fire": null,
    "lightning": null,
    "holy": null,
    "poison": null,
    "rot": null,
    "bleed": null,
    "frostbite": null,
    "sleep": null,
    "madness": null
  },
  {
    "name": "NAMELESS KING",
    "nightlord": "HEOLSTER",
    "night": "NIGHT 2",
    "standard": null,
    "slash": null,
    "strike": null,
    "pierce": null,
    "magic": null,
    "fire": null,
    "lightning": null,
    "holy": null,
    "poison": null,
    "rot": null,
    "bleed": null,
    "frostbite": null,
    "sleep": null,
    "madness": null
  },
  {
    "name": "NOX DRAGONKIN",
    "nightlord": "HEOLSTER",
    "night": "NIGHT 2",
    "standard": null,
    "slash": null,
    "strike": null,
    "pierce": null,
    "magic": null,
    "fire": null,
    "lightning": null,
    "holy": null,
    "poison": null,
    "rot": null,
    "bleed": null,
    "frostbite": null,
    "sleep": null,
    "madness": null
  }
]
